<?xml version="1.0"?>
<testResults>
  <FitNesseVersion>v20220815</FitNesseVersion>
  <rootPath>POCTestSuite.MeshDownload</rootPath>
  <result>
    <counts>
      <right>0</right>
      <wrong>0</wrong>
      <ignores>0</ignores>
      <exceptions>1</exceptions>
    </counts>
    <date>2022-11-02T16:51:34+01:00</date>
    <runTimeInMillis>83</runTimeInMillis>
    <content>&lt;div class="collapsible closed"&gt;&lt;ul&gt;&lt;li&gt;&lt;a href='#' class='expandall'&gt;Expand&lt;/a&gt;&lt;/li&gt;&lt;li&gt;&lt;a href='#' class='collapseall'&gt;Collapse&lt;/a&gt;&lt;/li&gt;&lt;/ul&gt;
	&lt;p class="title"&gt;Included page: &lt;a href="POCTestSuite.SetUp"&gt;.POCTestSuite.SetUp&lt;/a&gt; &lt;a href="POCTestSuite.SetUp?edit&amp;amp;redirectToReferer=true&amp;amp;redirectAction=" class="edit"&gt;(edit)&lt;/a&gt;&lt;/p&gt;
	&lt;div&gt;&lt;table&gt;
	&lt;tr class="slimRowTitle"&gt;
		&lt;td&gt;Import&lt;/td&gt;
	&lt;/tr&gt;
	&lt;tr class="slimRowColor0"&gt;
		&lt;td&gt;&lt;span class="pass"&gt;ragnar&lt;/span&gt;&lt;/td&gt;
	&lt;/tr&gt;
&lt;/table&gt;
&lt;/div&gt;
&lt;/div&gt;
&lt;br/&gt;&lt;table&gt;
	&lt;tr class="slimRowTitle"&gt;
		&lt;td&gt;script&lt;/td&gt;
		&lt;td&gt;&lt;span class="pass"&gt;mesh download&lt;/span&gt;&lt;/td&gt;
	&lt;/tr&gt;
	&lt;tr class="slimRowColor2"&gt;
		&lt;td&gt;set MDL binary &lt;span class="error"&gt;No Method setMDLBinary[1] in class ragnar.MeshDownload.
 Available methods:
displayConfig() -&amp;gt; class java.lang.String
equals(java.lang.Object) -&amp;gt; boolean
getClass() -&amp;gt; class java.lang.Class
hashCode() -&amp;gt; int
notify() -&amp;gt; void
notifyAll() -&amp;gt; void
run() -&amp;gt; class java.lang.String
setChannel(java.lang.String) -&amp;gt; void
setMDLConfigFile(java.lang.String) -&amp;gt; void
setVersion(java.lang.String) -&amp;gt; void
toString() -&amp;gt; class java.lang.String
wait() -&amp;gt; void
wait(long) -&amp;gt; void
wait(long, int) -&amp;gt; void&lt;/span&gt;&lt;/td&gt;
		&lt;td&gt;test channel&lt;/td&gt;
	&lt;/tr&gt;
	&lt;tr class="slimRowColor5"&gt;
		&lt;td&gt;set MDL config file&lt;/td&gt;
		&lt;td&gt;a_file&lt;/td&gt;
	&lt;/tr&gt;
	&lt;tr class="slimRowColor9"&gt;
		&lt;td&gt;show&lt;/td&gt;
		&lt;td&gt;display config&lt;/td&gt;
	&lt;td&gt;channel: preprod | version: latest | MDL config file: a_file&lt;/td&gt;&lt;/tr&gt;
&lt;/table&gt;
&lt;br/&gt;&lt;br/&gt;&lt;br/&gt;&lt;div class="collapsible closed teardown"&gt;&lt;ul&gt;&lt;li&gt;&lt;a href='#' class='expandall'&gt;Expand&lt;/a&gt;&lt;/li&gt;&lt;li&gt;&lt;a href='#' class='collapseall'&gt;Collapse&lt;/a&gt;&lt;/li&gt;&lt;/ul&gt;
	&lt;p class="title"&gt;Included page: &lt;a href="POCTestSuite.TearDown"&gt;.POCTestSuite.TearDown&lt;/a&gt; &lt;a href="POCTestSuite.TearDown?edit&amp;amp;redirectToReferer=true&amp;amp;redirectAction=" class="edit"&gt;(edit)&lt;/a&gt;&lt;/p&gt;
	&lt;div&gt;&lt;/div&gt;
&lt;/div&gt;
</content>
    <relativePageName>MeshDownload</relativePageName>
    <instructions>
      <instructionResult>
        <instruction>{id='import_0_0', instruction='import', path='ragnar'}</instruction>
        <slimResult>pass(ragnar)</slimResult>
        <expectation>
          <status>pass</status>
          <instructionId>import_0_0</instructionId>
          <col>0</col>
          <row>1</row>
          <type>ImportExpectation</type>
          <evaluationMessage>ragnar</evaluationMessage>
        </expectation>
      </instructionResult>
      <instructionResult>
        <instruction>{id='scriptTable_1_0', instruction='make', instanceName='scriptTableActor', className='MeshDownload', args=[]}</instruction>
        <slimResult>pass(mesh download)</slimResult>
        <expectation>
          <status>pass</status>
          <instructionId>scriptTable_1_0</instructionId>
          <col>1</col>
          <row>0</row>
          <type>ConstructionExpectation</type>
          <evaluationMessage>mesh download</evaluationMessage>
        </expectation>
      </instructionResult>
      <instructionResult>
        <instruction>{id='scriptTable_1_1', instruction='call', instanceName='scriptTableActor', methodName='setMDLBinary', args=[test channel]}</instruction>
        <slimResult></slimResult>
        <expectation>
          <status>error</status>
          <instructionId>scriptTable_1_1</instructionId>
          <type>ScriptActionExpectation</type>
          <evaluationMessage>No Method setMDLBinary[1] in class ragnar.MeshDownload.
 Available methods:
displayConfig() -&gt; class java.lang.String
equals(java.lang.Object) -&gt; boolean
getClass() -&gt; class java.lang.Class
hashCode() -&gt; int
notify() -&gt; void
notifyAll() -&gt; void
run() -&gt; class java.lang.String
setChannel(java.lang.String) -&gt; void
setMDLConfigFile(java.lang.String) -&gt; void
setVersion(java.lang.String) -&gt; void
toString() -&gt; class java.lang.String
wait() -&gt; void
wait(long) -&gt; void
wait(long, int) -&gt; void</evaluationMessage>
        </expectation>
      </instructionResult>
      <instructionResult>
        <instruction>{id='scriptTable_1_2', instruction='call', instanceName='scriptTableActor', methodName='setMDLConfigFile', args=[a_file]}</instruction>
        <slimResult></slimResult>
        <expectation>
          <instructionId>scriptTable_1_2</instructionId>
          <col>0</col>
          <row>2</row>
          <type>ScriptActionExpectation</type>
        </expectation>
      </instructionResult>
      <instructionResult>
        <instruction>{id='scriptTable_1_3', instruction='call', instanceName='scriptTableActor', methodName='displayConfig', args=[]}</instruction>
        <slimResult></slimResult>
        <expectation>
          <instructionId>scriptTable_1_3</instructionId>
          <col>0</col>
          <row>3</row>
          <type>ShowActionExpectation</type>
        </expectation>
      </instructionResult>
    </instructions>
  </result>
  <executionLog>
    <testSystem>slim:fitnesse.slim.SlimService</testSystem>
    <command>/Users/ad21627/.sdkman/candidates/java/current/bin/java -cp /Users/ad21627/FitNesse/ragnar/ragnar.jar:/Users/ad21627/FitNesse/fitnesse-standalone.jar fitnesse.slim.SlimService 1</command>
    <exitCode>0</exitCode>
    <stdOut></stdOut>
    <stdErr></stdErr>
  </executionLog>
  <finalCounts>
    <right>0</right>
    <wrong>0</wrong>
    <ignores>0</ignores>
    <exceptions>1</exceptions>
  </finalCounts>
  <totalRunTimeInMillis>358</totalRunTimeInMillis>
</testResults>

